telemetrix_Barmaja/__init__.py
telemetrix_Barmaja/_version.py
telemetrix_Barmaja/telemetrixsync.py
telemetrix_Barmaja/examples/Checked/Light_Sensor_only_Print.py
telemetrix_Barmaja/examples/Checked/Ultra_LED_Buzzer.py
telemetrix_Barmaja/examples/Checked/blink.py
telemetrix_Barmaja/examples/Checked/button_to_led.py
telemetrix_Barmaja/examples/Checked/dht11_fan_serial_bridge.py
telemetrix_Barmaja/examples/Checked/led_fade.py
telemetrix_Barmaja/examples/Checked/light_sensor_fade_led.py
telemetrix_Barmaja/examples/Checked/light_sensor_led_on_off.py
telemetrix_Barmaja/examples/To be edited/find_port.py
telemetrix_Barmaja/examples/To be edited/hc05_two_leds_ldr_python.py
telemetrix_Barmaja/examples/To be edited/hc05_two_leds_python.py
telemetrix_Barmaja/examples/To be edited/keypad_4x4_lock.py
telemetrix_Barmaja/examples/To be edited/lm35_buzzer_alarm.py
telemetrix_Barmaja/examples/To be edited/lm35_fan_pwm.py
telemetrix_Barmaja/examples/To be edited/rfid_pn532_uid.py
telemetrix_Barmaja/examples/To be edited/rfid_rc522_serial_reader.py
telemetrix_Barmaja/examples/To be edited/rgb_pwm_cycle.py
telemetrix_Barmaja/examples/To be edited/servo_sweep.py
telemetrix_Barmaja/examples/To be edited/ultrasonic_5leds_bargraph.py
telemetrix_Barmaja/examples/To be edited/ultrasonic_buzzer_speed.py
telemetrix_Barmaja/examples/To be edited/ultrasonic_lcd.py
telemetrix_Barmaja/examples/To be edited/ultrasonic_lcd_telemetrix_Barmaja.py
telemetrix_Barmaja/examples/To be edited/ultrasonic_led.py
telemetrix_barmaja-1.0.0.dist-info/licenses/LICENSE
telemetrix_barmaja-1.0.0.dist-info/METADATA
telemetrix_barmaja-1.0.0.dist-info/WHEEL
telemetrix_barmaja-1.0.0.dist-info/top_level.txt
telemetrix_barmaja-1.0.0.dist-info/RECORD
